{
  "schemaVersion": 1,
  "id": "blockmeter",
  "version": "${version}",
  "environment": "*",    
  "entrypoints": {
    "client": [ "win.baruna.blockmeter.BlockMeterClient" ],
    "main": [ "win.baruna.blockmeter.BlockMeterServer" ]
  },
  "custom": {
      "xxxmodmenu:clientsideOnly": true
  },
  "mixins": [
    "blockmeter.mixins.json"
  ],
  "depends": {
    "fabricloader": ">=0.4.0",
    "fabric": "*"
  },
  
  "name": "Block Meter",
  "description": "A simple mod to measure your blocks!",
  "icon": "pack.png",
  "authors": [ "MadeOke", "Giselbaer" ],

  "contact": {
    "homepage": "https://www.curseforge.com/minecraft/mc-mods/blockmeterfabric",
    "sources": "https://github.com/gbl/BlockMeter",
    "issues": "https://github.com/gbl/BlockMeter/issues"
  },

  "license": "MIT"
}
